beam_integrals/__init__.py
beam_integrals/beam_types.py
beam_integrals/characteristic_equation_solvers.py
beam_integrals/exceptions.py
beam_integrals/integrals.py
beam_integrals/shell.py
beam_integrals-1.1.2.dist-info/DESCRIPTION.rst
beam_integrals-1.1.2.dist-info/METADATA
beam_integrals-1.1.2.dist-info/RECORD
beam_integrals-1.1.2.dist-info/WHEEL
beam_integrals-1.1.2.dist-info/entry_points.txt
beam_integrals-1.1.2.dist-info/metadata.json
beam_integrals-1.1.2.dist-info/top_level.txt
