Metadata-Version: 2.0
Name: beam-integrals
Version: 1.1.2
Summary: Console app and Python API for determining beam integrals of all 6 supported beam types, as described in D.D. Milasinovic, "The Finite Strip Method in Computational Mechanics" (ISBN 8680297194)
Home-page: https://github.com/petarmaric/beam_integrals/
Author: Petar Maric
Author-email: petarmaric@uns.ac.rs
License: BSD
Platform: any
Classifier: Development Status :: 5 - Production/Stable
Classifier: Environment :: Console
Classifier: Intended Audience :: Developers
Classifier: Intended Audience :: Science/Research
Classifier: License :: OSI Approved :: BSD License
Classifier: Operating System :: OS Independent
Classifier: Programming Language :: Python :: 2.6
Classifier: Programming Language :: Python :: 2.7
Classifier: Topic :: Scientific/Engineering
Classifier: Topic :: Scientific/Engineering :: Physics
Requires-Dist: friendly-name-mixin (>=1.0)
Requires-Dist: simple-plugins (>=1.0)
Requires-Dist: sympy (==0.7.1)
